README.md
setup.py
CmcClient/__init__.py
CmcClient/api_client.py
CmcClient/configuration.py
CmcClient/rest.py
CmcClient/api/__init__.py
CmcClient/api/default_api.py
CmcClient/models/__init__.py
CmcClient/models/cryptocurrency_info.py
CmcClient/models/cryptocurrency_info_urls.py
CmcClient/models/cryptocurrency_listings.py
CmcClient/models/cryptocurrency_map.py
CmcClient/models/global_metrics_historical_quote.py
CmcClient/models/global_metrics_quote.py
CmcClient/models/global_metrics_quotes_historical.py
CmcClient/models/global_metrics_quotes_latest.py
CmcClient/models/inline_response200.py
CmcClient/models/inline_response2001.py
CmcClient/models/inline_response2002.py
CmcClient/models/inline_response2003.py
CmcClient/models/inline_response2004.py
CmcClient/models/inline_response2004_data.py
CmcClient/models/inline_response2005.py
CmcClient/models/inline_response2006.py
CmcClient/models/inline_response2007.py
CmcClient/models/inline_response2008.py
CmcClient/models/inline_response2009.py
CmcClient/models/inline_response_default.py
CmcClient/models/inline_response_default1.py
CmcClient/models/platform.py
CmcClient/models/quote.py
CmcClient/models/status.py
cmc_client.egg-info/PKG-INFO
cmc_client.egg-info/SOURCES.txt
cmc_client.egg-info/dependency_links.txt
cmc_client.egg-info/requires.txt
cmc_client.egg-info/top_level.txt
test/__init__.py
test/test_cryptocurrency_info.py
test/test_cryptocurrency_info_urls.py
test/test_cryptocurrency_listings.py
test/test_cryptocurrency_map.py
test/test_default_api.py
test/test_global_metrics_historical_quote.py
test/test_global_metrics_quote.py
test/test_global_metrics_quotes_historical.py
test/test_global_metrics_quotes_latest.py
test/test_inline_response200.py
test/test_inline_response2001.py
test/test_inline_response2002.py
test/test_inline_response2003.py
test/test_inline_response2004.py
test/test_inline_response2004_data.py
test/test_inline_response2005.py
test/test_inline_response2006.py
test/test_inline_response2007.py
test/test_inline_response2008.py
test/test_inline_response2009.py
test/test_inline_response_default.py
test/test_inline_response_default1.py
test/test_platform.py
